{
  "keywords": [
    {
      "text": "red sea",
      "count": 32,
      "size": 100
    },
    {
      "text": "hormuz crisis",
      "count": 21,
      "size": 100
    },
    {
      "text": "and statistics",
      "count": 20,
      "size": 100
    },
    {
      "text": "due to",
      "count": 20,
      "size": 100
    },
    {
      "text": "in february",
      "count": 19,
      "size": 100
    },
    {
      "text": "baltic dry",
      "count": 19,
      "size": 100
    },
    {
      "text": "the iran",
      "count": 19,
      "size": 100
    },
    {
      "text": "jones act",
      "count": 18,
      "size": 100
    },
    {
      "text": "new york",
      "count": 18,
      "size": 100
    },
    {
      "text": "south china",
      "count": 16,
      "size": 100
    },
    {
      "text": "dry index",
      "count": 15,
      "size": 100
    },
    {
      "text": "to ease",
      "count": 15,
      "size": 100
    },
    {
      "text": "war in",
      "count": 15,
      "size": 100
    },
    {
      "text": "postal service",
      "count": 14,
      "size": 100
    },
    {
      "text": "나선 남해지방해양경찰청과 부산해양경찰서",
      "count": 13,
      "size": 100
    },
    {
      "text": "남해지방해양경찰청과 부산해양경찰서 소속",
      "count": 13,
      "size": 100
    },
    {
      "text": "특별단속에 나선 남해지방해양경찰청과",
      "count": 13,
      "size": 100
    },
    {
      "text": "hormuz disruption",
      "count": 13,
      "size": 100
    },
    {
      "text": "부산해양경찰서 소속 경찰관들로",
      "count": 13,
      "size": 100
    },
    {
      "text": "경찰관들로 구성된 전담반이",
      "count": 13,
      "size": 100
    },
    {
      "text": "선박에서 단속활동을 벌이고",
      "count": 13,
      "size": 100
    },
    {
      "text": "소속 경찰관들로 구성된",
      "count": 13,
      "size": 100
    },
    {
      "text": "구성된 전담반이 19일",
      "count": 13,
      "size": 100
    },
    {
      "text": "한 선박에서 단속활동을",
      "count": 13,
      "size": 100
    },
    {
      "text": "단속활동을 벌이고 있다",
      "count": 13,
      "size": 100
    },
    {
      "text": "석유 유통 특별단속에",
      "count": 13,
      "size": 100
    },
    {
      "text": "유통 특별단속에 나선",
      "count": 13,
      "size": 100
    },
    {
      "text": "전담반이 19일 부산",
      "count": 13,
      "size": 100
    },
    {
      "text": "동구 부산항 4부두에",
      "count": 13,
      "size": 100
    },
    {
      "text": "부산항 4부두에 정박",
      "count": 13,
      "size": 100
    },
    {
      "text": "벌이고 있다. 해경은",
      "count": 13,
      "size": 100
    },
    {
      "text": "불법 유통 특별단속",
      "count": 13,
      "size": 100
    },
    {
      "text": "4부두에 정박 중인",
      "count": 13,
      "size": 100
    },
    {
      "text": "19일 부산 동구",
      "count": 13,
      "size": 100
    },
    {
      "text": "부산 동구 부산항",
      "count": 13,
      "size": 100
    },
    {
      "text": "중인 한 선박에서",
      "count": 13,
      "size": 100
    },
    {
      "text": "해상 기름 불법",
      "count": 13,
      "size": 100
    },
    {
      "text": "기름 불법 유통",
      "count": 13,
      "size": 100
    },
    {
      "text": "해상 석유 유통",
      "count": 13,
      "size": 100
    },
    {
      "text": "정박 중인 한",
      "count": 13,
      "size": 100
    },
    {
      "text": "chain disruptions",
      "count": 12,
      "size": 100
    },
    {
      "text": "사태 여파 고유가…부산항",
      "count": 12,
      "size": 100
    },
    {
      "text": "여파 고유가…부산항 해상",
      "count": 12,
      "size": 100
    },
    {
      "text": "고유가…부산항 해상 기름",
      "count": 12,
      "size": 100
    },
    {
      "text": "c.h. robinson",
      "count": 12,
      "size": 100
    },
    {
      "text": "유통 특별단속 해상",
      "count": 12,
      "size": 100
    },
    {
      "text": "특별단속 해상 석유",
      "count": 12,
      "size": 100
    },
    {
      "text": "있다. 해경은 중동",
      "count": 12,
      "size": 100
    },
    {
      "text": "demand for",
      "count": 12,
      "size": 100
    },
    {
      "text": "global oil",
      "count": 12,
      "size": 100
    },
    {
      "text": "해경은 중동 사태",
      "count": 12,
      "size": 100
    },
    {
      "text": "중동 사태 여파로",
      "count": 12,
      "size": 100
    },
    {
      "text": "as hormuz",
      "count": 12,
      "size": 100
    },
    {
      "text": "iran conflict",
      "count": 11,
      "size": 100
    },
    {
      "text": "index rises",
      "count": 11,
      "size": 100
    },
    {
      "text": "올해 첫 물류센터",
      "count": 11,
      "size": 100
    },
    {
      "text": "to bypass",
      "count": 11,
      "size": 100
    },
    {
      "text": "need to",
      "count": 11,
      "size": 100
    },
    {
      "text": "statistics indexbox",
      "count": 10,
      "size": 100
    },
    {
      "text": "robinson worldwide",
      "count": 10,
      "size": 100
    },
    {
      "text": "trump temporarily",
      "count": 10,
      "size": 100
    },
    {
      "text": "through strait",
      "count": 10,
      "size": 100
    },
    {
      "text": "hormuz closure",
      "count": 10,
      "size": 100
    },
    {
      "text": "global energy",
      "count": 10,
      "size": 100
    },
    {
      "text": "bypass strait",
      "count": 10,
      "size": 100
    },
    {
      "text": "east tensions",
      "count": 10,
      "size": 100
    },
    {
      "text": "fujairah oil",
      "count": 10,
      "size": 100
    },
    {
      "text": "china sea",
      "count": 10,
      "size": 100
    },
    {
      "text": "to help",
      "count": 10,
      "size": 100
    },
    {
      "text": "federal reserve",
      "count": 9,
      "size": 90
    },
    {
      "text": "disrupts global",
      "count": 9,
      "size": 90
    },
    {
      "text": "fuel surcharges",
      "count": 9,
      "size": 90
    },
    {
      "text": "persian gulf",
      "count": 9,
      "size": 90
    },
    {
      "text": "시흥, 안성, 용인",
      "count": 9,
      "size": 90
    },
    {
      "text": "strikes on",
      "count": 9,
      "size": 90
    },
    {
      "text": "수도권 남부 지역",
      "count": 9,
      "size": 90
    },
    {
      "text": "등 수도권 남부",
      "count": 9,
      "size": 90
    },
    {
      "text": "fears of",
      "count": 9,
      "size": 90
    },
    {
      "text": "warns of",
      "count": 9,
      "size": 90
    },
    {
      "text": "to boost",
      "count": 9,
      "size": 90
    },
    {
      "text": "surge in",
      "count": 9,
      "size": 90
    },
    {
      "text": "to hold",
      "count": 9,
      "size": 90
    },
    {
      "text": "war is",
      "count": 9,
      "size": 90
    },
    {
      "text": "semiconductor supply",
      "count": 8,
      "size": 80
    },
    {
      "text": "temporarily waives",
      "count": 8,
      "size": 80
    },
    {
      "text": "keeps stranglehold",
      "count": 8,
      "size": 80
    },
    {
      "text": "partnership with",
      "count": 8,
      "size": 80
    },
    {
      "text": "stranglehold on",
      "count": 8,
      "size": 80
    },
    {
      "text": "worldwide, inc",
      "count": 8,
      "size": 80
    },
    {
      "text": "dalilah’s law",
      "count": 8,
      "size": 80
    },
    {
      "text": "bab el-mandeb",
      "count": 8,
      "size": 80
    },
    {
      "text": "in singapore",
      "count": 8,
      "size": 80
    },
    {
      "text": "the loadstar",
      "count": 8,
      "size": 80
    },
    {
      "text": "chain crisis",
      "count": 8,
      "size": 80
    },
    {
      "text": "급유가 가능한 항만은",
      "count": 8,
      "size": 80
    },
    {
      "text": "2025 annual",
      "count": 8,
      "size": 80
    },
    {
      "text": "안성, 용인, 이천",
      "count": 8,
      "size": 80
    },
    {
      "text": "동탄, 마장, 시흥",
      "count": 8,
      "size": 80
    },
    {
      "text": "마장, 시흥, 안성",
      "count": 8,
      "size": 80
    },
    {
      "text": "attacks on",
      "count": 8,
      "size": 80
    }
  ],
  "total_keywords": 50199,
  "generated_at": "2026-03-19T02:36:23Z"
}