{
  "stock_index": {
    "items": {
      "KOSPI": {
        "name": "KOSPI",
        "current": 2650.32,
        "previous": 2640.15,
        "change": 10.17,
        "change_percent": 0.39,
        "data": [
          {
            "time": "2026-05-26",
            "value": 2592.84
          },
          {
            "time": "2026-05-27",
            "value": 2600.12
          },
          {
            "time": "2026-05-28",
            "value": 2602.01
          },
          {
            "time": "2026-05-29",
            "value": 2592.36
          },
          {
            "time": "2026-05-30",
            "value": 2573.84
          },
          {
            "time": "2026-05-31",
            "value": 2595.66
          },
          {
            "time": "2026-06-01",
            "value": 2580.42
          },
          {
            "time": "2026-06-02",
            "value": 2592.7
          },
          {
            "time": "2026-06-03",
            "value": 2588.13
          },
          {
            "time": "2026-06-04",
            "value": 2610.93
          },
          {
            "time": "2026-06-05",
            "value": 2596.38
          },
          {
            "time": "2026-06-06",
            "value": 2585.69
          },
          {
            "time": "2026-06-07",
            "value": 2590.95
          },
          {
            "time": "2026-06-08",
            "value": 2614.19
          },
          {
            "time": "2026-06-09",
            "value": 2634.64
          },
          {
            "time": "2026-06-10",
            "value": 2646.96
          },
          {
            "time": "2026-06-11",
            "value": 2665.89
          },
          {
            "time": "2026-06-12",
            "value": 2679.18
          },
          {
            "time": "2026-06-13",
            "value": 2659.38
          },
          {
            "time": "2026-06-14",
            "value": 2648.12
          },
          {
            "time": "2026-06-15",
            "value": 2635.03
          },
          {
            "time": "2026-06-16",
            "value": 2654.23
          },
          {
            "time": "2026-06-17",
            "value": 2677.5
          },
          {
            "time": "2026-06-18",
            "value": 2670.43
          },
          {
            "time": "2026-06-19",
            "value": 2671.34
          },
          {
            "time": "2026-06-20",
            "value": 2663.84
          },
          {
            "time": "2026-06-21",
            "value": 2670.9
          },
          {
            "time": "2026-06-22",
            "value": 2688.99
          },
          {
            "time": "2026-06-23",
            "value": 2704.98
          },
          {
            "time": "2026-06-24",
            "value": 2720.63
          },
          {
            "time": "2026-06-25",
            "value": 2712.97
          }
        ]
      },
      "KOSDAQ": {
        "name": "KOSDAQ",
        "current": 820.45,
        "previous": 815.2,
        "change": 5.25,
        "change_percent": 0.64,
        "data": [
          {
            "time": "2026-05-26",
            "value": 797.59
          },
          {
            "time": "2026-05-27",
            "value": 805.74
          },
          {
            "time": "2026-05-28",
            "value": 808.79
          },
          {
            "time": "2026-05-29",
            "value": 807.93
          },
          {
            "time": "2026-05-30",
            "value": 798.76
          },
          {
            "time": "2026-05-31",
            "value": 806.38
          },
          {
            "time": "2026-06-01",
            "value": 807.48
          },
          {
            "time": "2026-06-02",
            "value": 801.77
          },
          {
            "time": "2026-06-03",
            "value": 796.68
          },
          {
            "time": "2026-06-04",
            "value": 786.81
          },
          {
            "time": "2026-06-05",
            "value": 786.69
          },
          {
            "time": "2026-06-06",
            "value": 783.11
          },
          {
            "time": "2026-06-07",
            "value": 779.22
          },
          {
            "time": "2026-06-08",
            "value": 775.78
          },
          {
            "time": "2026-06-09",
            "value": 772.01
          },
          {
            "time": "2026-06-10",
            "value": 776.56
          },
          {
            "time": "2026-06-11",
            "value": 775.01
          },
          {
            "time": "2026-06-12",
            "value": 776.43
          },
          {
            "time": "2026-06-13",
            "value": 774.99
          },
          {
            "time": "2026-06-14",
            "value": 766.39
          },
          {
            "time": "2026-06-15",
            "value": 771.4
          },
          {
            "time": "2026-06-16",
            "value": 761.96
          },
          {
            "time": "2026-06-17",
            "value": 766.13
          },
          {
            "time": "2026-06-18",
            "value": 763.23
          },
          {
            "time": "2026-06-19",
            "value": 769.67
          },
          {
            "time": "2026-06-20",
            "value": 769.18
          },
          {
            "time": "2026-06-21",
            "value": 765.1
          },
          {
            "time": "2026-06-22",
            "value": 766.31
          },
          {
            "time": "2026-06-23",
            "value": 763.17
          },
          {
            "time": "2026-06-24",
            "value": 754.64
          },
          {
            "time": "2026-06-25",
            "value": 749.77
          }
        ]
      },
      "S&P500": {
        "name": "S&P 500",
        "current": 5890.12,
        "previous": 5875.3,
        "change": 14.82,
        "change_percent": 0.25,
        "data": [
          {
            "time": "2026-05-26",
            "value": 5803.61
          },
          {
            "time": "2026-05-27",
            "value": 5809.71
          },
          {
            "time": "2026-05-28",
            "value": 5781.27
          },
          {
            "time": "2026-05-29",
            "value": 5820.35
          },
          {
            "time": "2026-05-30",
            "value": 5855.68
          },
          {
            "time": "2026-05-31",
            "value": 5817.94
          },
          {
            "time": "2026-06-01",
            "value": 5791.73
          },
          {
            "time": "2026-06-02",
            "value": 5816.19
          },
          {
            "time": "2026-06-03",
            "value": 5847.91
          },
          {
            "time": "2026-06-04",
            "value": 5850.46
          },
          {
            "time": "2026-06-05",
            "value": 5864.72
          },
          {
            "time": "2026-06-06",
            "value": 5833.29
          },
          {
            "time": "2026-06-07",
            "value": 5838.33
          },
          {
            "time": "2026-06-08",
            "value": 5805.41
          },
          {
            "time": "2026-06-09",
            "value": 5787.1
          },
          {
            "time": "2026-06-10",
            "value": 5754.16
          },
          {
            "time": "2026-06-11",
            "value": 5729.19
          },
          {
            "time": "2026-06-12",
            "value": 5747.41
          },
          {
            "time": "2026-06-13",
            "value": 5767.57
          },
          {
            "time": "2026-06-14",
            "value": 5758.28
          },
          {
            "time": "2026-06-15",
            "value": 5763.55
          },
          {
            "time": "2026-06-16",
            "value": 5775.73
          },
          {
            "time": "2026-06-17",
            "value": 5784.91
          },
          {
            "time": "2026-06-18",
            "value": 5818.8
          },
          {
            "time": "2026-06-19",
            "value": 5832.45
          },
          {
            "time": "2026-06-20",
            "value": 5851.38
          },
          {
            "time": "2026-06-21",
            "value": 5861.46
          },
          {
            "time": "2026-06-22",
            "value": 5861.96
          },
          {
            "time": "2026-06-23",
            "value": 5841.17
          },
          {
            "time": "2026-06-24",
            "value": 5855.52
          },
          {
            "time": "2026-06-25",
            "value": 5877.12
          }
        ]
      },
      "NASDAQ": {
        "name": "NASDAQ",
        "current": 19250.5,
        "previous": 19180.2,
        "change": 70.3,
        "change_percent": 0.37,
        "data": [
          {
            "time": "2026-05-26",
            "value": 18969.68
          },
          {
            "time": "2026-05-27",
            "value": 18872.68
          },
          {
            "time": "2026-05-28",
            "value": 18970.51
          },
          {
            "time": "2026-05-29",
            "value": 18875.84
          },
          {
            "time": "2026-05-30",
            "value": 18885.94
          },
          {
            "time": "2026-05-31",
            "value": 18804.81
          },
          {
            "time": "2026-06-01",
            "value": 18778.62
          },
          {
            "time": "2026-06-02",
            "value": 18855.8
          },
          {
            "time": "2026-06-03",
            "value": 18755.84
          },
          {
            "time": "2026-06-04",
            "value": 18749.96
          },
          {
            "time": "2026-06-05",
            "value": 18729.55
          },
          {
            "time": "2026-06-06",
            "value": 18767.36
          },
          {
            "time": "2026-06-07",
            "value": 18691.51
          },
          {
            "time": "2026-06-08",
            "value": 18752.74
          },
          {
            "time": "2026-06-09",
            "value": 18792.01
          },
          {
            "time": "2026-06-10",
            "value": 18869.07
          },
          {
            "time": "2026-06-11",
            "value": 18932.63
          },
          {
            "time": "2026-06-12",
            "value": 18945.13
          },
          {
            "time": "2026-06-13",
            "value": 18944.26
          },
          {
            "time": "2026-06-14",
            "value": 18897.13
          },
          {
            "time": "2026-06-15",
            "value": 18853.67
          },
          {
            "time": "2026-06-16",
            "value": 18945.63
          },
          {
            "time": "2026-06-17",
            "value": 18907.23
          },
          {
            "time": "2026-06-18",
            "value": 19004.64
          },
          {
            "time": "2026-06-19",
            "value": 19014.59
          },
          {
            "time": "2026-06-20",
            "value": 19031.18
          },
          {
            "time": "2026-06-21",
            "value": 18962.9
          },
          {
            "time": "2026-06-22",
            "value": 19031.23
          },
          {
            "time": "2026-06-23",
            "value": 18967.74
          },
          {
            "time": "2026-06-24",
            "value": 19040.61
          },
          {
            "time": "2026-06-25",
            "value": 19088.55
          }
        ]
      }
    }
  },
  "exchange_rate": {
    "items": {
      "USD": {
        "name": "USD/KRW",
        "current": 1432.5,
        "previous": 1428.2,
        "change": 4.3,
        "change_percent": 0.3,
        "data": [
          {
            "time": "2026-05-26",
            "value": 1413.34
          },
          {
            "time": "2026-05-27",
            "value": 1413.35
          },
          {
            "time": "2026-05-28",
            "value": 1415.82
          },
          {
            "time": "2026-05-29",
            "value": 1413.61
          },
          {
            "time": "2026-05-30",
            "value": 1411.94
          },
          {
            "time": "2026-05-31",
            "value": 1416.33
          },
          {
            "time": "2026-06-01",
            "value": 1417.35
          },
          {
            "time": "2026-06-02",
            "value": 1418.24
          },
          {
            "time": "2026-06-03",
            "value": 1421.82
          },
          {
            "time": "2026-06-04",
            "value": 1427.7
          },
          {
            "time": "2026-06-05",
            "value": 1423.89
          },
          {
            "time": "2026-06-06",
            "value": 1430.28
          },
          {
            "time": "2026-06-07",
            "value": 1434.13
          },
          {
            "time": "2026-06-08",
            "value": 1437.93
          },
          {
            "time": "2026-06-09",
            "value": 1432.27
          },
          {
            "time": "2026-06-10",
            "value": 1432.75
          },
          {
            "time": "2026-06-11",
            "value": 1433.1
          },
          {
            "time": "2026-06-12",
            "value": 1438.2
          },
          {
            "time": "2026-06-13",
            "value": 1435.34
          },
          {
            "time": "2026-06-14",
            "value": 1437.04
          },
          {
            "time": "2026-06-15",
            "value": 1442.54
          },
          {
            "time": "2026-06-16",
            "value": 1435.89
          },
          {
            "time": "2026-06-17",
            "value": 1437.37
          },
          {
            "time": "2026-06-18",
            "value": 1430.92
          },
          {
            "time": "2026-06-19",
            "value": 1430.41
          },
          {
            "time": "2026-06-20",
            "value": 1436.15
          },
          {
            "time": "2026-06-21",
            "value": 1431.7
          },
          {
            "time": "2026-06-22",
            "value": 1425.97
          },
          {
            "time": "2026-06-23",
            "value": 1422.89
          },
          {
            "time": "2026-06-24",
            "value": 1424.89
          },
          {
            "time": "2026-06-25",
            "value": 1429.1
          }
        ]
      },
      "EUR": {
        "name": "EUR/KRW",
        "current": 1485.3,
        "previous": 1480.5,
        "change": 4.8,
        "change_percent": 0.32,
        "data": [
          {
            "time": "2026-05-26",
            "value": 1465.73
          },
          {
            "time": "2026-05-27",
            "value": 1462.96
          },
          {
            "time": "2026-05-28",
            "value": 1457.4
          },
          {
            "time": "2026-05-29",
            "value": 1454.2
          },
          {
            "time": "2026-05-30",
            "value": 1460.48
          },
          {
            "time": "2026-05-31",
            "value": 1452.54
          },
          {
            "time": "2026-06-01",
            "value": 1449.67
          },
          {
            "time": "2026-06-02",
            "value": 1451.37
          },
          {
            "time": "2026-06-03",
            "value": 1442.93
          },
          {
            "time": "2026-06-04",
            "value": 1450.65
          },
          {
            "time": "2026-06-05",
            "value": 1459.24
          },
          {
            "time": "2026-06-06",
            "value": 1453.28
          },
          {
            "time": "2026-06-07",
            "value": 1455.3
          },
          {
            "time": "2026-06-08",
            "value": 1462.79
          },
          {
            "time": "2026-06-09",
            "value": 1456.64
          },
          {
            "time": "2026-06-10",
            "value": 1448.87
          },
          {
            "time": "2026-06-11",
            "value": 1444.56
          },
          {
            "time": "2026-06-12",
            "value": 1447.06
          },
          {
            "time": "2026-06-13",
            "value": 1452.59
          },
          {
            "time": "2026-06-14",
            "value": 1450.25
          },
          {
            "time": "2026-06-15",
            "value": 1443.79
          },
          {
            "time": "2026-06-16",
            "value": 1438.22
          },
          {
            "time": "2026-06-17",
            "value": 1444.86
          },
          {
            "time": "2026-06-18",
            "value": 1448.63
          },
          {
            "time": "2026-06-19",
            "value": 1451.0
          },
          {
            "time": "2026-06-20",
            "value": 1449.73
          },
          {
            "time": "2026-06-21",
            "value": 1449.59
          },
          {
            "time": "2026-06-22",
            "value": 1441.07
          },
          {
            "time": "2026-06-23",
            "value": 1437.93
          },
          {
            "time": "2026-06-24",
            "value": 1443.77
          },
          {
            "time": "2026-06-25",
            "value": 1441.4
          }
        ]
      },
      "JPY": {
        "name": "JPY/KRW",
        "current": 9.25,
        "previous": 9.2,
        "change": 0.05,
        "change_percent": 0.54,
        "data": [
          {
            "time": "2026-05-26",
            "value": 9.07
          },
          {
            "time": "2026-05-27",
            "value": 9.0
          },
          {
            "time": "2026-05-28",
            "value": 8.91
          },
          {
            "time": "2026-05-29",
            "value": 8.85
          },
          {
            "time": "2026-05-30",
            "value": 8.81
          },
          {
            "time": "2026-05-31",
            "value": 8.74
          },
          {
            "time": "2026-06-01",
            "value": 8.66
          },
          {
            "time": "2026-06-02",
            "value": 8.64
          },
          {
            "time": "2026-06-03",
            "value": 8.61
          },
          {
            "time": "2026-06-04",
            "value": 8.63
          },
          {
            "time": "2026-06-05",
            "value": 8.7
          },
          {
            "time": "2026-06-06",
            "value": 8.78
          },
          {
            "time": "2026-06-07",
            "value": 8.76
          },
          {
            "time": "2026-06-08",
            "value": 8.82
          },
          {
            "time": "2026-06-09",
            "value": 8.73
          },
          {
            "time": "2026-06-10",
            "value": 8.68
          },
          {
            "time": "2026-06-11",
            "value": 8.63
          },
          {
            "time": "2026-06-12",
            "value": 8.62
          },
          {
            "time": "2026-06-13",
            "value": 8.69
          },
          {
            "time": "2026-06-14",
            "value": 8.72
          },
          {
            "time": "2026-06-15",
            "value": 8.8
          },
          {
            "time": "2026-06-16",
            "value": 8.85
          },
          {
            "time": "2026-06-17",
            "value": 8.89
          },
          {
            "time": "2026-06-18",
            "value": 8.87
          },
          {
            "time": "2026-06-19",
            "value": 8.81
          },
          {
            "time": "2026-06-20",
            "value": 8.77
          },
          {
            "time": "2026-06-21",
            "value": 8.8
          },
          {
            "time": "2026-06-22",
            "value": 8.83
          },
          {
            "time": "2026-06-23",
            "value": 8.74
          },
          {
            "time": "2026-06-24",
            "value": 8.77
          },
          {
            "time": "2026-06-25",
            "value": 8.81
          }
        ]
      },
      "CNY": {
        "name": "CNY/KRW",
        "current": 196.5,
        "previous": 195.8,
        "change": 0.7,
        "change_percent": 0.36,
        "data": [
          {
            "time": "2026-05-26",
            "value": 194.23
          },
          {
            "time": "2026-05-27",
            "value": 195.03
          },
          {
            "time": "2026-05-28",
            "value": 195.18
          },
          {
            "time": "2026-05-29",
            "value": 195.26
          },
          {
            "time": "2026-05-30",
            "value": 194.33
          },
          {
            "time": "2026-05-31",
            "value": 193.84
          },
          {
            "time": "2026-06-01",
            "value": 193.09
          },
          {
            "time": "2026-06-02",
            "value": 193.01
          },
          {
            "time": "2026-06-03",
            "value": 192.12
          },
          {
            "time": "2026-06-04",
            "value": 191.75
          },
          {
            "time": "2026-06-05",
            "value": 191.21
          },
          {
            "time": "2026-06-06",
            "value": 190.12
          },
          {
            "time": "2026-06-07",
            "value": 189.8
          },
          {
            "time": "2026-06-08",
            "value": 190.0
          },
          {
            "time": "2026-06-09",
            "value": 190.46
          },
          {
            "time": "2026-06-10",
            "value": 191.3
          },
          {
            "time": "2026-06-11",
            "value": 189.89
          },
          {
            "time": "2026-06-12",
            "value": 189.23
          },
          {
            "time": "2026-06-13",
            "value": 188.63
          },
          {
            "time": "2026-06-14",
            "value": 187.33
          },
          {
            "time": "2026-06-15",
            "value": 188.4
          },
          {
            "time": "2026-06-16",
            "value": 189.1
          },
          {
            "time": "2026-06-17",
            "value": 189.62
          },
          {
            "time": "2026-06-18",
            "value": 188.88
          },
          {
            "time": "2026-06-19",
            "value": 187.69
          },
          {
            "time": "2026-06-20",
            "value": 187.18
          },
          {
            "time": "2026-06-21",
            "value": 186.8
          },
          {
            "time": "2026-06-22",
            "value": 186.17
          },
          {
            "time": "2026-06-23",
            "value": 184.68
          },
          {
            "time": "2026-06-24",
            "value": 183.39
          },
          {
            "time": "2026-06-25",
            "value": 183.73
          }
        ]
      }
    }
  },
  "interest_rate": {
    "items": {
      "KR": {
        "name": "한국 기준금리",
        "current": 3.0,
        "previous": 3.0,
        "change": 0,
        "change_percent": 0,
        "data": [
          {
            "time": "2026-05-26",
            "value": 3.02
          },
          {
            "time": "2026-05-27",
            "value": 3.04
          },
          {
            "time": "2026-05-28",
            "value": 3.04
          },
          {
            "time": "2026-05-29",
            "value": 3.05
          },
          {
            "time": "2026-05-30",
            "value": 3.03
          },
          {
            "time": "2026-05-31",
            "value": 3.05
          },
          {
            "time": "2026-06-01",
            "value": 3.05
          },
          {
            "time": "2026-06-02",
            "value": 3.08
          },
          {
            "time": "2026-06-03",
            "value": 3.06
          },
          {
            "time": "2026-06-04",
            "value": 3.06
          },
          {
            "time": "2026-06-05",
            "value": 3.08
          },
          {
            "time": "2026-06-06",
            "value": 3.09
          },
          {
            "time": "2026-06-07",
            "value": 3.09
          },
          {
            "time": "2026-06-08",
            "value": 3.08
          },
          {
            "time": "2026-06-09",
            "value": 3.07
          },
          {
            "time": "2026-06-10",
            "value": 3.09
          },
          {
            "time": "2026-06-11",
            "value": 3.1
          },
          {
            "time": "2026-06-12",
            "value": 3.11
          },
          {
            "time": "2026-06-13",
            "value": 3.09
          },
          {
            "time": "2026-06-14",
            "value": 3.08
          },
          {
            "time": "2026-06-15",
            "value": 3.08
          },
          {
            "time": "2026-06-16",
            "value": 3.06
          },
          {
            "time": "2026-06-17",
            "value": 3.07
          },
          {
            "time": "2026-06-18",
            "value": 3.08
          },
          {
            "time": "2026-06-19",
            "value": 3.07
          },
          {
            "time": "2026-06-20",
            "value": 3.08
          },
          {
            "time": "2026-06-21",
            "value": 3.05
          },
          {
            "time": "2026-06-22",
            "value": 3.05
          },
          {
            "time": "2026-06-23",
            "value": 3.04
          },
          {
            "time": "2026-06-24",
            "value": 3.05
          },
          {
            "time": "2026-06-25",
            "value": 3.04
          }
        ]
      },
      "US": {
        "name": "미국 기준금리",
        "current": 4.5,
        "previous": 4.5,
        "change": 0,
        "change_percent": 0,
        "data": [
          {
            "time": "2026-05-26",
            "value": 4.5
          },
          {
            "time": "2026-05-27",
            "value": 4.51
          },
          {
            "time": "2026-05-28",
            "value": 4.52
          },
          {
            "time": "2026-05-29",
            "value": 4.51
          },
          {
            "time": "2026-05-30",
            "value": 4.51
          },
          {
            "time": "2026-05-31",
            "value": 4.51
          },
          {
            "time": "2026-06-01",
            "value": 4.52
          },
          {
            "time": "2026-06-02",
            "value": 4.53
          },
          {
            "time": "2026-06-03",
            "value": 4.53
          },
          {
            "time": "2026-06-04",
            "value": 4.54
          },
          {
            "time": "2026-06-05",
            "value": 4.55
          },
          {
            "time": "2026-06-06",
            "value": 4.57
          },
          {
            "time": "2026-06-07",
            "value": 4.58
          },
          {
            "time": "2026-06-08",
            "value": 4.58
          },
          {
            "time": "2026-06-09",
            "value": 4.6
          },
          {
            "time": "2026-06-10",
            "value": 4.59
          },
          {
            "time": "2026-06-11",
            "value": 4.61
          },
          {
            "time": "2026-06-12",
            "value": 4.63
          },
          {
            "time": "2026-06-13",
            "value": 4.62
          },
          {
            "time": "2026-06-14",
            "value": 4.63
          },
          {
            "time": "2026-06-15",
            "value": 4.61
          },
          {
            "time": "2026-06-16",
            "value": 4.59
          },
          {
            "time": "2026-06-17",
            "value": 4.59
          },
          {
            "time": "2026-06-18",
            "value": 4.6
          },
          {
            "time": "2026-06-19",
            "value": 4.58
          },
          {
            "time": "2026-06-20",
            "value": 4.57
          },
          {
            "time": "2026-06-21",
            "value": 4.57
          },
          {
            "time": "2026-06-22",
            "value": 4.59
          },
          {
            "time": "2026-06-23",
            "value": 4.61
          },
          {
            "time": "2026-06-24",
            "value": 4.58
          },
          {
            "time": "2026-06-25",
            "value": 4.59
          }
        ]
      },
      "EU": {
        "name": "EU 기준금리",
        "current": 3.0,
        "previous": 3.0,
        "change": 0,
        "change_percent": 0,
        "data": [
          {
            "time": "2026-05-26",
            "value": 2.98
          },
          {
            "time": "2026-05-27",
            "value": 2.98
          },
          {
            "time": "2026-05-28",
            "value": 2.99
          },
          {
            "time": "2026-05-29",
            "value": 3.0
          },
          {
            "time": "2026-05-30",
            "value": 3.01
          },
          {
            "time": "2026-05-31",
            "value": 3.02
          },
          {
            "time": "2026-06-01",
            "value": 3.0
          },
          {
            "time": "2026-06-02",
            "value": 3.0
          },
          {
            "time": "2026-06-03",
            "value": 2.98
          },
          {
            "time": "2026-06-04",
            "value": 3.0
          },
          {
            "time": "2026-06-05",
            "value": 3.03
          },
          {
            "time": "2026-06-06",
            "value": 3.02
          },
          {
            "time": "2026-06-07",
            "value": 3.0
          },
          {
            "time": "2026-06-08",
            "value": 3.01
          },
          {
            "time": "2026-06-09",
            "value": 3.0
          },
          {
            "time": "2026-06-10",
            "value": 3.0
          },
          {
            "time": "2026-06-11",
            "value": 3.0
          },
          {
            "time": "2026-06-12",
            "value": 3.02
          },
          {
            "time": "2026-06-13",
            "value": 3.04
          },
          {
            "time": "2026-06-14",
            "value": 3.02
          },
          {
            "time": "2026-06-15",
            "value": 3.04
          },
          {
            "time": "2026-06-16",
            "value": 3.03
          },
          {
            "time": "2026-06-17",
            "value": 3.01
          },
          {
            "time": "2026-06-18",
            "value": 2.99
          },
          {
            "time": "2026-06-19",
            "value": 3.01
          },
          {
            "time": "2026-06-20",
            "value": 3.01
          },
          {
            "time": "2026-06-21",
            "value": 3.02
          },
          {
            "time": "2026-06-22",
            "value": 3.0
          },
          {
            "time": "2026-06-23",
            "value": 3.0
          },
          {
            "time": "2026-06-24",
            "value": 2.97
          },
          {
            "time": "2026-06-25",
            "value": 3.0
          }
        ]
      },
      "JP": {
        "name": "일본 기준금리",
        "current": 0.25,
        "previous": 0.25,
        "change": 0,
        "change_percent": 0,
        "data": [
          {
            "time": "2026-05-26",
            "value": 0.25
          },
          {
            "time": "2026-05-27",
            "value": 0.26
          },
          {
            "time": "2026-05-28",
            "value": 0.27
          },
          {
            "time": "2026-05-29",
            "value": 0.26
          },
          {
            "time": "2026-05-30",
            "value": 0.27
          },
          {
            "time": "2026-05-31",
            "value": 0.27
          },
          {
            "time": "2026-06-01",
            "value": 0.28
          },
          {
            "time": "2026-06-02",
            "value": 0.27
          },
          {
            "time": "2026-06-03",
            "value": 0.26
          },
          {
            "time": "2026-06-04",
            "value": 0.26
          },
          {
            "time": "2026-06-05",
            "value": 0.27
          },
          {
            "time": "2026-06-06",
            "value": 0.27
          },
          {
            "time": "2026-06-07",
            "value": 0.26
          },
          {
            "time": "2026-06-08",
            "value": 0.26
          },
          {
            "time": "2026-06-09",
            "value": 0.26
          },
          {
            "time": "2026-06-10",
            "value": 0.25
          },
          {
            "time": "2026-06-11",
            "value": 0.25
          },
          {
            "time": "2026-06-12",
            "value": 0.24
          },
          {
            "time": "2026-06-13",
            "value": 0.24
          },
          {
            "time": "2026-06-14",
            "value": 0.25
          },
          {
            "time": "2026-06-15",
            "value": 0.25
          },
          {
            "time": "2026-06-16",
            "value": 0.26
          },
          {
            "time": "2026-06-17",
            "value": 0.27
          },
          {
            "time": "2026-06-18",
            "value": 0.26
          },
          {
            "time": "2026-06-19",
            "value": 0.26
          },
          {
            "time": "2026-06-20",
            "value": 0.25
          },
          {
            "time": "2026-06-21",
            "value": 0.25
          },
          {
            "time": "2026-06-22",
            "value": 0.25
          },
          {
            "time": "2026-06-23",
            "value": 0.24
          },
          {
            "time": "2026-06-24",
            "value": 0.23
          },
          {
            "time": "2026-06-25",
            "value": 0.23
          }
        ]
      }
    }
  },
  "generated_at": "2026-06-25T03:54:51Z"
}